{
    "video_id": "BMSf51TYsTQ",
    "title": "😍 Star Wars Backpacks",
    "channel": "iJustine",
    "channel_id": "UCey_c7U86mJGz1VJWH5CYPA",
    "subscriber_count": 7100000,
    "upload_date": "2018-01-26T21:23:09Z",
    "video_url": "https://www.youtube.com/watch?v=BMSf51TYsTQ",
    "category": "Science & Technology",
    "tags": [
        "ijustine",
        "star wars backpacks"
    ],
    "views": 146442,
    "likes": 6237,
    "comments_count": 694,
    "description": "🔔 PLEASE SUBSCRIBE: http://www.youtube.com/subscription_center?add_user=ijustine\n💕GET MY PINK iJUSTINE CABLES HERE: https://geni.us/wnIN\n\n🎥GET MY EDITING PLUGIN:  https://mvfx.co/mKeynote-with-iJustine\n🎶 MUSIC I USE - http://share.epidemicsound.com/NNNGs\n\n✅FRIEND ME HERE:\nhttp://twitter.com/ijustine\nhttp://instagram.com/ijustine\nhttp://facebook.com/ijustine\nhttps://tiktok.com/@ijustine\nhttps://snapchat.com/add/ijustine\n\n🐷 MY NEW PROJECT: http://twitter.com/jpig\n🎤 PODCAST: http://youtube.com/samebrain\n\n———\n\n\n🎥 WHAT I USE TO MAKE VIDEOS 📷 \n\nCAMERAS:\nSony a7 IV - https://geni.us/U70407\nSony a1 -  https://amzn.to/3jScz3h\nSony a7s III - https://geni.us/mAtruYL \nInsta 360 ONE X3 - https://geni.us/2mPGn\nInsta 360 ONE RS - https://geni.us/8kJHun\nInsta 360 GO2 - https://geni.us/cZGA6ST\n\nLENSES:\nNew Sony GM 24-70mm ii - https://geni.us/liSjf\nOlder Sony GM 24-70mm - https://amzn.to/3DWqJau\nNew Sony Sony 20-70mm - https://geni.us/irEgHq\nSony GM 16-35mm - https://geni.us/vwolf\nSony GM 50mm - https://geni.us/gxDS\nSony GM 135mm - https://geni.us/R46usnU\nSony GM 85mm - https://geni.us/diFZAJ\n\nAUDIO: \nSennheiser AVX Digital Wireless - https://geni.us/eaUR\nSony XLR Adapter - https://geni.us/TfEu\nSony Hot Shoe Shotgun - https://geni.us/eqim0\nTiny Sony Microphone - https://geni.us/hjmjD\nDJI Mics - https://geni.us/pxN9Vw6\nRode Podcaster Pro II - https://geni.us/OmAta4o\nPodcaster Mic - https://geni.us/6KKHkB\nElgato Wave 3 Mic - https://geni.us/DXX7\n\nDRONES:\nDJI Mavic 3 - https://geni.us/RU6m\nDJI Mini 3 - https://geni.us/Ga4H\nDJI Air 2S - https://geni.us/RaBW61\n\nLIGHTING:\nAputure 600d Pro - https://geni.us/uKRvYQ\nAputure Light Dome II - https://geni.us/M1MUS\nAputure Amaran 200d - https://geni.us/8I5a\nAputure 35in Light Dome - https://geni.us/DOJNEo\nAputure Lantern Softbox - https://geni.us/0b4zBFR\n\nSony CF Express A 160g + Card Reader- https://geni.us/Gku22\nSony CF Express A 800g - https://geni.us/p3RtyR\n\n——— \nThese links are affiliate and by using them you’re helping out my channel! Thank you! \n——— \n\nBECOME A CHANNEL MEMBER: https://www.youtube.com/channel/UCey_c7U86mJGz1VJWH5CYPA/join",
    "description_links": [
        "http://www.youtube.com/subscription_center?add_user=ijustine",
        "https://geni.us/wnIN",
        "https://mvfx.co/mKeynote-with-iJustine",
        "http://share.epidemicsound.com/NNNGs",
        "http://twitter.com/ijustine",
        "http://instagram.com/ijustine",
        "http://facebook.com/ijustine",
        "https://tiktok.com/@ijustine",
        "https://snapchat.com/add/ijustine",
        "http://twitter.com/jpig",
        "http://youtube.com/samebrain",
        "https://geni.us/U70407",
        "https://amzn.to/3jScz3h",
        "https://geni.us/mAtruYL",
        "https://geni.us/2mPGn",
        "https://geni.us/8kJHun",
        "https://geni.us/cZGA6ST",
        "https://geni.us/liSjf",
        "https://amzn.to/3DWqJau",
        "https://geni.us/irEgHq",
        "https://geni.us/vwolf",
        "https://geni.us/gxDS",
        "https://geni.us/R46usnU",
        "https://geni.us/diFZAJ",
        "https://geni.us/eaUR",
        "https://geni.us/TfEu",
        "https://geni.us/eqim0",
        "https://geni.us/hjmjD",
        "https://geni.us/pxN9Vw6",
        "https://geni.us/OmAta4o",
        "https://geni.us/6KKHkB",
        "https://geni.us/DXX7",
        "https://geni.us/RU6m",
        "https://geni.us/Ga4H",
        "https://geni.us/RaBW61",
        "https://geni.us/uKRvYQ",
        "https://geni.us/M1MUS",
        "https://geni.us/8I5a",
        "https://geni.us/DOJNEo",
        "https://geni.us/0b4zBFR",
        "https://geni.us/Gku22",
        "https://geni.us/p3RtyR",
        "https://www.youtube.com/channel/UCey_c7U86mJGz1VJWH5CYPA/join"
    ],
    "transcript": "- Hey guys! How's it going? This is gonna be a very quick video, but this has been a very highly requested question that I get all the time. Not only do I get this question online, but I get it in actual real life out in the wild. That question is, \"Where did you get your backpack?\" I've been using this backpack for almost a year now, and I am obsessed with it. Now, not only do I have this backpack, but I have another one as well. These two I've pretty much had in rotation over the past two years. They're by Loungefly. This is not sponsored. Ed actually bought me this one for my birthday last year, and then shortly after, I got this one because I loved this one so much. This one has cartoon baby Star Wars characters on it. And of course, this one has a beautiful Stormtrooper pattern on it. I'm obsessed. And I'm making this video mostly because people have been asking me so much where I get them. One of the things that I've been struggling with for a very long time is trying to find the perfect mini backpack. One that I can fit all of my items in and it not be too big but not be too small. This is the perfect size. One thing that I do wish that it had was some sort of a pocket inside. 'Cause right now you've only got two pockets. You've got this big one and then this small one. And because I'm paranoid, I don't like to put my wallet inside here because someone could easily just open that up if you're walking and take it right out. So I like to have that hidden inside. So if there was an inside zipper part, that would be so incredible. 'Cause then I wouldn't have to be paranoid. I mean right now all someone's gonna steal is ChapStick if they get in here. So because I've been using these for the past year, I wanted to see if they had any more. And guess what? They have so many! This company, I feel like, has bought the rights to pretty much everything. Marvel, Pokemon. If there's something that you're into, they probably have it. Not only do they have backpacks, they have tiny little purses and clutches. They have so many things, it's kind of overwhelming. But for me, I'm a backpack fan, and I gotta show you guys the two new ones that I just got. (object clatters) Oh, that wasn't the best reveal ever, but here they are! This one specifically, when I saw this I started freaking out. This one has to be fairly new because I never saw it, and I have been searching probably the past year just for something else that I liked as much as I like these two. I really like this one, this is the Darth Vader backpack, because it's all black, and it pretty much matches anything. But unless I'm wearing Rebel Alliance gear, I don't really think I'm gonna be matching this much. 'Cause this color scheme is way easier to match. I mean clearly if I'm wearing Star Wars backpacks, I'm not really that concerned with if things are matching or not. But either way, you guys are probably gonna see these in Instagram, you're gonna see them on Twitter. And now you'll know, if someone Googles, \"Where did Justine get her backpack?\" this video will show up, and it will have all the answers and all of the links in the description. Again, not sponsored. But honestly you guys have been asking so much and I feel like these are so perfect for all of you. I love the new Pokemon one that they have. It's black like this but it has little Pokeballs all over it. I had to draw the line somewhere (laughs). So after these two, and I feel like I'm set for quite a while. So let me know what you guys think. Do you guys have a favorite? I'm not really sure which one I like the best because I feel like all of these are so different, it really depends on what my outfit is. I wonder if they have a BB-8 one. Wait a minute. Is this a mini backpack? They do have a BB-8 mini school backpack as well, but I don't think it's as small as this one is, though. I don't need it. I don't need it. I don't need it. You don't need it! You don't need it! Well thank you guys so much for watching! I will see you in my next video. Let me know what you guys think of these backpacks. Do you already have one? Do you have any other Loungefly products? If so, let me know in the comments below, and I'm so sorry if you're gonna go shopping now. But don't worry. It's worth it! (playful music)",
    "transcript_keywords": [
        "backpack",
        "guys",
        "Star Wars backpacks",
        "Hey guys",
        "Star Wars",
        "year",
        "backpacks",
        "inside",
        "feel",
        "video",
        "question",
        "mini backpack",
        "past year",
        "Darth Vader backpack",
        "things",
        "Wars backpacks",
        "perfect",
        "past",
        "small",
        "pretty"
    ],
    "transcript_entities": [
        [
            "the past year",
            "DATE"
        ],
        [
            "Loungefly",
            "GPE"
        ],
        [
            "Pokemon",
            "PERSON"
        ],
        [
            "Instagram",
            "ORG"
        ],
        [
            "Twitter",
            "ORG"
        ],
        [
            "a minute",
            "TIME"
        ],
        [
            "Googles",
            "PERSON"
        ],
        [
            "One",
            "CARDINAL"
        ],
        [
            "ChapStick",
            "ORG"
        ],
        [
            "Pokemon",
            "ORG"
        ],
        [
            "the past two years",
            "DATE"
        ],
        [
            "Ed",
            "PERSON"
        ],
        [
            "Darth Vader",
            "PERSON"
        ],
        [
            "last year",
            "DATE"
        ],
        [
            "Justine",
            "PERSON"
        ],
        [
            "two",
            "CARDINAL"
        ],
        [
            "Rebel Alliance",
            "ORG"
        ],
        [
            "almost a year",
            "DATE"
        ]
    ]
}