{
    "video_id": "r77-BphNlbQ",
    "title": "Top 5 Apps on F-Droid That Are Not on Google Play Store",
    "channel": "TechWiser",
    "channel_id": "UCdp6GUwjKscp5ST4M4WgIpw",
    "subscriber_count": 2200000,
    "upload_date": "2017-08-06T14:00:31Z",
    "video_url": "https://www.youtube.com/watch?v=r77-BphNlbQ",
    "category": "Science & Technology",
    "tags": [
        "Mrinal Saha",
        "TechWiser",
        "Apps on F-Droid",
        "Top 5 Apps on F-Droid That Are Not on Google Play Store",
        "Not on Google Play Store",
        "Top 10 F-droid Best Apps (Not on Google Play)"
    ],
    "views": 32832,
    "likes": 698,
    "comments_count": 82,
    "description": "What's F-Droid you ask?\n\nWell, it’s kind of like Google play store, but it only hosts the apps that are free and open source. \n\nYou can either download F-droid first and then download these apps, by searching on it (like you do on Google Play) or you can simply sideload the following apps.\n\n\n1. Yalp store \nhttps://f-droid.org/packages/link.standen.michael.phonesaver/\n\n2. Chromium SWE Updater https://f-droid.org/packages/chromiumupdater.bamless.com.chromiumsweupdater/\n\n3. Clover\nhttps://f-droid.org/packages/org.floens.chan/\n\n4. NewPipe \nhttps://f-droid.org/packages/org.schabi.newpipe/\n\n5. DNS66 \nhttps://f-droid.org/packages/org.jak_linux.dns66/\n\nFew others worth checking out.\n\n\nAdAway - best ad blocker, needs root though\nhttps://f-droid.org/packages/org.adaway/\n\nLightning Browser - fast browser with ad blocking\nhttps://f-droid.org/packages/acr.browser.lightning/\n\nAsciiCam a pixellated style camera app. weird but fun\nhttps://f-droid.org/packages/com.dozingcatsoftware.asciicam\n\ncSploit network hacking and man in the middle attack needs root\nhttps://f-droid.org/packages/org.csploit.android/ \n\nPhone saver - save file from share menu\nhttps://f-droid.org/packages/link.standen.michael.phonesaver/\n\nAntennaPod - a decent podcast app, but not the best\nhttps://f-droid.org/packages/de.danoeh.antennapod/\n\nYou can find some other F-Droid apps here.\nhttp://techwiser.com/f-droid-best-apps/\n\nYou can reach me here\n\nWebsite - http://techwiser.com/\nYouTube - https://www.youtube.com/techwiser\nFacebook -https://www.facebook.com/techwiser\nTwitter - https://twitter.com/TechWiser\nInstagram - https://www.instagram.com/techwiser\n\nWhich background music did I use?\n\n\nWhat camera do I use? \nCanon 70D\n\nWhat mike do I use?\nBlue Yeti and Video Mic pro (depends on requirement)\n\nWhat tripod do I use?\nManfrotto MVKBFR\n\nWhat video editor do I use?\nFinal Cut Pro\n\nMy computer do I use?\niMac 2015 for editing and a ThinkPad for casual work",
    "description_links": [
        "https://f-droid.org/packages/link.standen.michael.phonesaver/",
        "https://f-droid.org/packages/chromiumupdater.bamless.com.chromiumsweupdater/",
        "https://f-droid.org/packages/org.floens.chan/",
        "https://f-droid.org/packages/org.schabi.newpipe/",
        "https://f-droid.org/packages/org.jak_linux.dns66/",
        "https://f-droid.org/packages/org.adaway/",
        "https://f-droid.org/packages/acr.browser.lightning/",
        "https://f-droid.org/packages/com.dozingcatsoftware.asciicam",
        "https://f-droid.org/packages/org.csploit.android/",
        "https://f-droid.org/packages/link.standen.michael.phonesaver/",
        "https://f-droid.org/packages/de.danoeh.antennapod/",
        "http://techwiser.com/f-droid-best-apps/",
        "http://techwiser.com/",
        "https://www.youtube.com/techwiser",
        "https://www.facebook.com/techwiser",
        "https://twitter.com/TechWiser",
        "https://www.instagram.com/techwiser"
    ],
    "transcript": "No manual transcript available",
    "transcript_keywords": [
        "manual transcript",
        "manual",
        "transcript"
    ],
    "transcript_entities": []
}